abrconnection/__init__.py
abrconnection/interface.py
abrconnection-0.1.0.dist-info/LICENSE.txt
abrconnection-0.1.0.dist-info/METADATA
abrconnection-0.1.0.dist-info/WHEEL
abrconnection-0.1.0.dist-info/top_level.txt
abrconnection-0.1.0.dist-info/RECORD
