Metadata-Version: 2.1
Name: abrconnection
Version: 0.1.0
Summary: An interface between Python and Autonomous Battle Royale
Home-page: https://github.com/griffinteller/abrconnection
Author: Griffin Teller
Author-email: griffinteller@gmail.com
License: MIT
Platform: UNKNOWN
Classifier: Development Status :: 2 - Pre-Alpha
Classifier: License :: OSI Approved :: MIT License
Classifier: Programming Language :: Python :: 3
Classifier: Topic :: Software Development :: Libraries
Classifier: Topic :: Software Development :: Libraries :: Python Modules
Classifier: Intended Audience :: Education
Requires-Python: >=3.6
